{"trial_id": "07", "hyperparameters": {"space": [{"class_name": "Float", "config": {"name": "learning_rate", "default": 1e-05, "conditions": [], "min_value": 1e-05, "max_value": 0.001, "step": null, "sampling": "log"}}, {"class_name": "Float", "config": {"name": "epsilon", "default": 1e-07, "conditions": [], "min_value": 1e-07, "max_value": 1e-05, "step": null, "sampling": "log"}}, {"class_name": "Float", "config": {"name": "beta_1", "default": 0.8, "conditions": [], "min_value": 0.8, "max_value": 0.9, "step": null, "sampling": "reverse_log"}}, {"class_name": "Float", "config": {"name": "beta_2", "default": 0.8, "conditions": [], "min_value": 0.8, "max_value": 0.9, "step": null, "sampling": "reverse_log"}}], "values": {"learning_rate": 3.0658625710638904e-05, "epsilon": 1.2598966327198347e-06, "beta_1": 0.8009831436409914, "beta_2": 0.832276197359421}}, "metrics": {"metrics": {"loss": {"direction": "min", "observations": [{"value": [0.5781360268592834], "step": 98}]}, "binary_accuracy": {"direction": "max", "observations": [{"value": [0.6428098678588867], "step": 98}]}, "val_loss": {"direction": "min", "observations": [{"value": [0.6036840677261353], "step": 98}]}, "val_binary_accuracy": {"direction": "max", "observations": [{"value": [0.5753099322319031], "step": 98}]}}}, "score": 0.6428098678588867, "best_step": 98, "status": "COMPLETED", "message": null}