{"trial_id": "01", "hyperparameters": {"space": [{"class_name": "Float", "config": {"name": "learning_rate", "default": 1e-05, "conditions": [], "min_value": 1e-05, "max_value": 0.001, "step": null, "sampling": "log"}}, {"class_name": "Float", "config": {"name": "epsilon", "default": 1e-07, "conditions": [], "min_value": 1e-07, "max_value": 1e-05, "step": null, "sampling": "log"}}, {"class_name": "Float", "config": {"name": "beta_1", "default": 0.8, "conditions": [], "min_value": 0.8, "max_value": 0.9, "step": null, "sampling": "reverse_log"}}, {"class_name": "Float", "config": {"name": "beta_2", "default": 0.8, "conditions": [], "min_value": 0.8, "max_value": 0.9, "step": null, "sampling": "reverse_log"}}], "values": {"learning_rate": 0.0007777133391633722, "epsilon": 1.6502768197012983e-07, "beta_1": 0.8904352074071191, "beta_2": 0.8139251626394243}}, "metrics": {"metrics": {"loss": {"direction": "min", "observations": [{"value": [0.5896157622337341], "step": 24}]}, "binary_accuracy": {"direction": "max", "observations": [{"value": [0.6029605269432068], "step": 24}]}, "val_loss": {"direction": "min", "observations": [{"value": [0.6027601361274719], "step": 24}]}, "val_binary_accuracy": {"direction": "max", "observations": [{"value": [0.5732632875442505], "step": 24}]}}}, "score": 0.6029605269432068, "best_step": 24, "status": "COMPLETED", "message": null}